hello_tjkpolisher-0.4.1.dist-info/METADATA
hello_tjkpolisher-0.4.1.dist-info/WHEEL
hello_tjkpolisher/__init__.py
hello_tjkpolisher/randomness.py
hello_tjkpolisher/who.py
hello_tjkpolisher-0.4.1.dist-info/RECORD
