Metadata-Version: 2.1
Name: hello-tjkpolisher
Version: 0.4.1
Summary: The Python program I'm distributing for the first time ever
Author-Email: tjkpolisher <jktak5609@gmail.com>
License: MIT
Project-URL: Homepage, https://github.com/tjkpolisher/hello-tjkpolisher
Project-URL: Bug tracker, https://github.com/tjkpolisher/hello-tjkpolisher/issues
Requires-Python: >=3.8
